regpyhdfe/__init__.py
regpyhdfe/regpyhdfe.py
regpyhdfe/utils.py
regpyhdfe-0.0.10.dist-info/LICENSE
regpyhdfe-0.0.10.dist-info/METADATA
regpyhdfe-0.0.10.dist-info/WHEEL
regpyhdfe-0.0.10.dist-info/top_level.txt
regpyhdfe-0.0.10.dist-info/RECORD
