Metadata-Version: 2.1
Name: regpyhdfe
Version: 0.0.10
Summary: Simple wrapper for PyHDFE
Home-page: https://github.com/lod531/regPyHDFE
Author: Andrius Buinovskij
Author-email: andriusb@ethz.ch
License: UNKNOWN
Platform: UNKNOWN
Classifier: Programming Language :: Python :: 3
Classifier: License :: OSI Approved :: MIT License
Classifier: Operating System :: OS Independent
Requires-Python: >=3.6
Requires-Dist: numpy
Requires-Dist: pandas
Requires-Dist: patsy
Requires-Dist: pyhdfe
Requires-Dist: statsmodels
